[{"Year": "Dec-10", "Heavy Truck Fatalities": 3, "Heavy Truck Fatalities - rolling 12 month average": 74},
{"Year": "Jan-11", "Heavy Truck Fatalities": 2, "Heavy Truck Fatalities - rolling 12 month average": 64},
{"Year": "Feb-11", "Heavy Truck Fatalities": 4, "Heavy Truck Fatalities - rolling 12 month average": 62},
{"Year": "Mar-11", "Heavy Truck Fatalities": 6, "Heavy Truck Fatalities - rolling 12 month average": 59},
{"Year": "Apr-11", "Heavy Truck Fatalities": 3, "Heavy Truck Fatalities - rolling 12 month average": 56},
{"Year": "May-11", "Heavy Truck Fatalities": 4, "Heavy Truck Fatalities - rolling 12 month average": 54},
{"Year": "Jun-11", "Heavy Truck Fatalities": 4, "Heavy Truck Fatalities - rolling 12 month average": 51},
{"Year": "Jul-11", "Heavy Truck Fatalities": 5, "Heavy Truck Fatalities - rolling 12 month average": 52},
{"Year": "Aug-11", "Heavy Truck Fatalities": 14, "Heavy Truck Fatalities - rolling 12 month average": 64},
{"Year": "Sep-11", "Heavy Truck Fatalities": 4, "Heavy Truck Fatalities - rolling 12 month average": 59},
{"Year": "Oct-11", "Heavy Truck Fatalities": 5, "Heavy Truck Fatalities - rolling 12 month average": 57},
{"Year": "Nov-11", "Heavy Truck Fatalities": 5, "Heavy Truck Fatalities - rolling 12 month average": 59},
{"Year": "Dec-11", "Heavy Truck Fatalities": 7, "Heavy Truck Fatalities - rolling 12 month average": 63},
{"Year": "Jan-12", "Heavy Truck Fatalities": 9, "Heavy Truck Fatalities - rolling 12 month average": 70},
{"Year": "Feb-12", "Heavy Truck Fatalities": 4, "Heavy Truck Fatalities - rolling 12 month average": 70},
{"Year": "Mar-12", "Heavy Truck Fatalities": 7, "Heavy Truck Fatalities - rolling 12 month average": 71},
{"Year": "Apr-12", "Heavy Truck Fatalities": 5, "Heavy Truck Fatalities - rolling 12 month average": 73},
{"Year": "May-12", "Heavy Truck Fatalities": 7, "Heavy Truck Fatalities - rolling 12 month average": 76},
{"Year": "Jun-12", "Heavy Truck Fatalities": 6, "Heavy Truck Fatalities - rolling 12 month average": 78},
{"Year": "Jul-12", "Heavy Truck Fatalities": 3, "Heavy Truck Fatalities - rolling 12 month average": 76},
{"Year": "Aug-12", "Heavy Truck Fatalities": 6, "Heavy Truck Fatalities - rolling 12 month average": 68},
{"Year": "Sep-12", "Heavy Truck Fatalities": 7, "Heavy Truck Fatalities - rolling 12 month average": 71},
{"Year": "Oct-12", "Heavy Truck Fatalities": 6, "Heavy Truck Fatalities - rolling 12 month average": 72},
{"Year": "Nov-12", "Heavy Truck Fatalities": 8, "Heavy Truck Fatalities - rolling 12 month average": 75},
{"Year": "Dec-12", "Heavy Truck Fatalities": 4, "Heavy Truck Fatalities - rolling 12 month average": 72},
{"Year": "Jan-13", "Heavy Truck Fatalities": 1, "Heavy Truck Fatalities - rolling 12 month average": 64},
{"Year": "Feb-13", "Heavy Truck Fatalities": 5, "Heavy Truck Fatalities - rolling 12 month average": 65},
{"Year": "Mar-13", "Heavy Truck Fatalities": 2, "Heavy Truck Fatalities - rolling 12 month average": 60},
{"Year": "Apr-13", "Heavy Truck Fatalities": 5, "Heavy Truck Fatalities - rolling 12 month average": 60},
{"Year": "May-13", "Heavy Truck Fatalities": 4, "Heavy Truck Fatalities - rolling 12 month average": 57},
{"Year": "Jun-13", "Heavy Truck Fatalities": 8, "Heavy Truck Fatalities - rolling 12 month average": 59},
{"Year": "Jul-13", "Heavy Truck Fatalities": 5, "Heavy Truck Fatalities - rolling 12 month average": 61},
{"Year": "Aug-13", "Heavy Truck Fatalities": 7, "Heavy Truck Fatalities - rolling 12 month average": 62},
{"Year": "Sep-13", "Heavy Truck Fatalities": 2, "Heavy Truck Fatalities - rolling 12 month average": 57},
{"Year": "Oct-13", "Heavy Truck Fatalities": 7, "Heavy Truck Fatalities - rolling 12 month average": 58},
{"Year": "Nov-13", "Heavy Truck Fatalities": 4, "Heavy Truck Fatalities - rolling 12 month average": 54},
{"Year": "Dec-13", "Heavy Truck Fatalities": 3, "Heavy Truck Fatalities - rolling 12 month average": 53},
{"Year": "Jan-14", "Heavy Truck Fatalities": 6, "Heavy Truck Fatalities - rolling 12 month average": 58},
{"Year": "Feb-14", "Heavy Truck Fatalities": 8, "Heavy Truck Fatalities - rolling 12 month average": 61},
{"Year": "Mar-14", "Heavy Truck Fatalities": 4, "Heavy Truck Fatalities - rolling 12 month average": 63},
{"Year": "Apr-14", "Heavy Truck Fatalities": 4, "Heavy Truck Fatalities - rolling 12 month average": 62},
{"Year": "May-14", "Heavy Truck Fatalities": 9, "Heavy Truck Fatalities - rolling 12 month average": 67},
{"Year": "Jun-14", "Heavy Truck Fatalities": 1, "Heavy Truck Fatalities - rolling 12 month average": 60},
{"Year": "Jul-14", "Heavy Truck Fatalities": 3, "Heavy Truck Fatalities - rolling 12 month average": 58},
{"Year": "Aug-14", "Heavy Truck Fatalities": 4, "Heavy Truck Fatalities - rolling 12 month average": 55},
{"Year": "Sep-14", "Heavy Truck Fatalities": 3, "Heavy Truck Fatalities - rolling 12 month average": 56},
{"Year": "Oct-14", "Heavy Truck Fatalities": 2, "Heavy Truck Fatalities - rolling 12 month average": 51},
{"Year": "Nov-14", "Heavy Truck Fatalities": 6, "Heavy Truck Fatalities - rolling 12 month average": 53},
{"Year": "Dec-14", "Heavy Truck Fatalities": 1, "Heavy Truck Fatalities - rolling 12 month average": 51},
{"Year": "Jan-15", "Heavy Truck Fatalities": 6, "Heavy Truck Fatalities - rolling 12 month average": 51},
{"Year": "Feb-15", "Heavy Truck Fatalities": 3, "Heavy Truck Fatalities - rolling 12 month average": 46},
{"Year": "Mar-15", "Heavy Truck Fatalities": 5, "Heavy Truck Fatalities - rolling 12 month average": 47},
{"Year": "Apr-15", "Heavy Truck Fatalities": 3, "Heavy Truck Fatalities - rolling 12 month average": 46},
{"Year": "May-15", "Heavy Truck Fatalities": 8, "Heavy Truck Fatalities - rolling 12 month average": 45},
{"Year": "Jun-15", "Heavy Truck Fatalities": 5, "Heavy Truck Fatalities - rolling 12 month average": 49},
{"Year": "Jul-15", "Heavy Truck Fatalities": 4, "Heavy Truck Fatalities - rolling 12 month average": 50},
{"Year": "Aug-15", "Heavy Truck Fatalities": 5, "Heavy Truck Fatalities - rolling 12 month average": 51},
{"Year": "Sep-15", "Heavy Truck Fatalities": 2, "Heavy Truck Fatalities - rolling 12 month average": 50},
{"Year": "Oct-15", "Heavy Truck Fatalities": 6, "Heavy Truck Fatalities - rolling 12 month average": 54},
{"Year": "Nov-15", "Heavy Truck Fatalities": 7, "Heavy Truck Fatalities - rolling 12 month average": 55},
{"Year": "Dec-15", "Heavy Truck Fatalities": 3, "Heavy Truck Fatalities - rolling 12 month average": 57},
{"Year": "Jan-16", "Heavy Truck Fatalities": 1, "Heavy Truck Fatalities - rolling 12 month average": 52},
{"Year": "Feb-16", "Heavy Truck Fatalities": 2, "Heavy Truck Fatalities - rolling 12 month average": 51},
{"Year": "Mar-16", "Heavy Truck Fatalities": 11, "Heavy Truck Fatalities - rolling 12 month average": 57},
{"Year": "Apr-16", "Heavy Truck Fatalities": 7, "Heavy Truck Fatalities - rolling 12 month average": 61},
{"Year": "May-16", "Heavy Truck Fatalities": 5, "Heavy Truck Fatalities - rolling 12 month average": 58},
{"Year": "Jun-16", "Heavy Truck Fatalities": 5, "Heavy Truck Fatalities - rolling 12 month average": 58},
{"Year": "Jul-16", "Heavy Truck Fatalities": 0, "Heavy Truck Fatalities - rolling 12 month average": 54},
{"Year": "Aug-16", "Heavy Truck Fatalities": 3, "Heavy Truck Fatalities - rolling 12 month average": 52},
{"Year": "Sep-16", "Heavy Truck Fatalities": 9, "Heavy Truck Fatalities - rolling 12 month average": 59},
{"Year": "Oct-16", "Heavy Truck Fatalities": 5, "Heavy Truck Fatalities - rolling 12 month average": 58},
{"Year": "Nov-16", "Heavy Truck Fatalities": 5, "Heavy Truck Fatalities - rolling 12 month average": 56},
{"Year": "Dec-16", "Heavy Truck Fatalities": 3, "Heavy Truck Fatalities - rolling 12 month average": 56},
{"Year": "Jan-17", "Heavy Truck Fatalities": 8, "Heavy Truck Fatalities - rolling 12 month average": 63},
{"Year": "Feb-17", "Heavy Truck Fatalities": 7, "Heavy Truck Fatalities - rolling 12 month average": 68},
{"Year": "Mar-17", "Heavy Truck Fatalities": 5, "Heavy Truck Fatalities - rolling 12 month average": 62},
{"Year": "Apr-17", "Heavy Truck Fatalities": 7, "Heavy Truck Fatalities - rolling 12 month average": 62},
{"Year": "May-17", "Heavy Truck Fatalities": 9, "Heavy Truck Fatalities - rolling 12 month average": 66},
{"Year": "Jun-17", "Heavy Truck Fatalities": 6, "Heavy Truck Fatalities - rolling 12 month average": 67},
{"Year": "Jul-17", "Heavy Truck Fatalities": 13, "Heavy Truck Fatalities - rolling 12 month average": 80},
{"Year": "Aug-17", "Heavy Truck Fatalities": 7, "Heavy Truck Fatalities - rolling 12 month average": 84},
{"Year": "Sep-17", "Heavy Truck Fatalities": 4, "Heavy Truck Fatalities - rolling 12 month average": 79},
{"Year": "Oct-17", "Heavy Truck Fatalities": 5, "Heavy Truck Fatalities - rolling 12 month average": 79},
{"Year": "Nov-17", "Heavy Truck Fatalities": 4, "Heavy Truck Fatalities - rolling 12 month average": 78},
{"Year": "Dec-17", "Heavy Truck Fatalities": 4, "Heavy Truck Fatalities - rolling 12 month average": 79},
{"Year": "Jan-18", "Heavy Truck Fatalities": 7, "Heavy Truck Fatalities - rolling 12 month average": 78},
{"Year": "Feb-18", "Heavy Truck Fatalities": 7, "Heavy Truck Fatalities - rolling 12 month average": 78},
{"Year": "Mar-18", "Heavy Truck Fatalities": 4, "Heavy Truck Fatalities - rolling 12 month average": 77},
{"Year": "Apr-18", "Heavy Truck Fatalities": 5, "Heavy Truck Fatalities - rolling 12 month average": 75},
{"Year": "May-18", "Heavy Truck Fatalities": 4, "Heavy Truck Fatalities - rolling 12 month average": 70},
{"Year": "Jun-18", "Heavy Truck Fatalities": 1, "Heavy Truck Fatalities - rolling 12 month average": 65},
{"Year": "Jul-18", "Heavy Truck Fatalities": 4, "Heavy Truck Fatalities - rolling 12 month average": 56},
{"Year": "Aug-18", "Heavy Truck Fatalities": 8, "Heavy Truck Fatalities - rolling 12 month average": 57},
{"Year": "Sep-18", "Heavy Truck Fatalities": 3, "Heavy Truck Fatalities - rolling 12 month average": 56},
{"Year": "Oct-18", "Heavy Truck Fatalities": 5, "Heavy Truck Fatalities - rolling 12 month average": 56},
{"Year": "Nov-18", "Heavy Truck Fatalities": 3, "Heavy Truck Fatalities - rolling 12 month average": 55},
{"Year": "Dec-18", "Heavy Truck Fatalities": 1, "Heavy Truck Fatalities - rolling 12 month average": 52},
{"Year": "Jan-19", "Heavy Truck Fatalities": 5, "Heavy Truck Fatalities - rolling 12 month average": 50},
{"Year": "Feb-19", "Heavy Truck Fatalities": 5, "Heavy Truck Fatalities - rolling 12 month average": 48},
{"Year": "Mar-19", "Heavy Truck Fatalities": 10, "Heavy Truck Fatalities - rolling 12 month average": 54},
{"Year": "Apr-19", "Heavy Truck Fatalities": 6, "Heavy Truck Fatalities - rolling 12 month average": 55},
{"Year": "May-19", "Heavy Truck Fatalities": 7, "Heavy Truck Fatalities - rolling 12 month average": 58},
{"Year": "Jun-19", "Heavy Truck Fatalities": 6, "Heavy Truck Fatalities - rolling 12 month average": 63},
{"Year": "Jul-19", "Heavy Truck Fatalities": 4, "Heavy Truck Fatalities - rolling 12 month average": 63},
{"Year": "Aug-19", "Heavy Truck Fatalities": 0, "Heavy Truck Fatalities - rolling 12 month average": 55},
{"Year": "Sep-19", "Heavy Truck Fatalities": 3, "Heavy Truck Fatalities - rolling 12 month average": 55},
{"Year": "Oct-19", "Heavy Truck Fatalities": 6, "Heavy Truck Fatalities - rolling 12 month average": 56},
{"Year": "Nov-19", "Heavy Truck Fatalities": 5, "Heavy Truck Fatalities - rolling 12 month average": 58},
{"Year": "Dec-19", "Heavy Truck Fatalities": 0, "Heavy Truck Fatalities - rolling 12 month average": 57},
{"Year": "Jan-20", "Heavy Truck Fatalities": 8, "Heavy Truck Fatalities - rolling 12 month average": 60}]